requestselapsed/__init__.py
requestselapsed/api.py
requestselapsed/output.py
requestselapsed/plugin.py
pytest_requestselapsed-0.0.3.dist-info/LICENSE
pytest_requestselapsed-0.0.3.dist-info/METADATA
pytest_requestselapsed-0.0.3.dist-info/WHEEL
pytest_requestselapsed-0.0.3.dist-info/entry_points.txt
pytest_requestselapsed-0.0.3.dist-info/top_level.txt
pytest_requestselapsed-0.0.3.dist-info/RECORD
