Metadata-Version: 2.1
Name: pytest-requestselapsed
Version: 0.0.3
Summary: collect and show http requests elapsed time
Author-email: zt <330356463@qq.com>
License: MIT License        
Project-URL: Homepage, https://github.com/zhengtong0898/pytest-requestselapsed
Classifier: Programming Language :: Python :: 3
Classifier: License :: OSI Approved :: MIT License
Classifier: Operating System :: OS Independent
Requires-Python: >=3.6
License-File: LICENSE
